nanosandbox/__init__.py
nanosandbox/__pycache__/__init__.cpython-314.pyc
nanosandbox/_nanosandbox.abi3.so
nanosandbox/py.typed
nanosandbox-0.1.0.dist-info/METADATA
nanosandbox-0.1.0.dist-info/WHEEL
nanosandbox-0.1.0.dist-info/RECORD
