Metadata-Version: 2.4
Name: nanosandbox
Version: 0.1.0
Classifier: Development Status :: 3 - Alpha
Classifier: Intended Audience :: Developers
Classifier: License :: OSI Approved :: MIT License
Classifier: License :: OSI Approved :: Apache Software License
Classifier: Operating System :: POSIX :: Linux
Classifier: Operating System :: MacOS
Classifier: Operating System :: Microsoft :: Windows
Classifier: Programming Language :: Python :: 3
Classifier: Programming Language :: Python :: 3.8
Classifier: Programming Language :: Python :: 3.9
Classifier: Programming Language :: Python :: 3.10
Classifier: Programming Language :: Python :: 3.11
Classifier: Programming Language :: Python :: 3.12
Classifier: Programming Language :: Rust
Classifier: Topic :: Security
Summary: Lightweight cross-platform sandbox for secure code execution
Keywords: sandbox,container,security,isolation,cross-platform
License: MIT
Requires-Python: >=3.8
Project-URL: Documentation, https://github.com/Erio-Harrison/nanosandbox#readme
Project-URL: Homepage, https://github.com/Erio-Harrison/nanosandbox
Project-URL: Repository, https://github.com/Erio-Harrison/nanosandbox
